{
    "Version": "2012-10-17",
    "Statement": [
        {
            "Sid": "EC2FullAccess",
            "Effect": "Allow",
            "Action": "ec2:*",
            "Resource": "*"
        },
        {
            "Sid": "ELBFullAccess",
            "Effect": "Allow",
            "Action": "elasticloadbalancing:*",
            "Resource": "*"
        },
        {
            "Sid": "AutoScalingFullAccess",
            "Effect": "Allow",
            "Action": "autoscaling:*",
            "Resource": "*"
        },
        {
            "Sid": "ECRFullAccess",
            "Effect": "Allow",
            "Action": "ecr:*",
            "Resource": "*"
        },
        {
            "Sid": "LambdaFullAccess",
            "Effect": "Allow",
            "Action": "lambda:*",
            "Resource": "arn:aws:lambda:*:*:function:kubestock-*"
        },
        {
            "Sid": "CloudWatchLogsFullAccess",
            "Effect": "Allow",
            "Action": "logs:*",
            "Resource": "arn:aws:logs:*:*:log-group:/aws/lambda/kubestock-*"
        },
        {
            "Sid": "EventBridgeFullAccess",
            "Effect": "Allow",
            "Action": "events:*",
            "Resource": "arn:aws:events:*:*:rule/kubestock-*"
        },
        {
            "Sid": "S3BackendFullAccess",
            "Effect": "Allow",
            "Action": "s3:*",
            "Resource": [
                "arn:aws:s3:::kubestock-terraform-state",
                "arn:aws:s3:::kubestock-terraform-state/*"
            ]
        },
        {
            "Sid": "SSMParameterStore",
            "Effect": "Allow",
            "Action": "ssm:*",
            "Resource": "arn:aws:ssm:*:*:parameter/kubestock/*"
        },
        {
            "Sid": "RDSFullAccess",
            "Effect": "Allow",
            "Action": "rds:*",
            "Resource": [
                "arn:aws:rds:*:*:db:kubestock-*",
                "arn:aws:rds:*:*:subgrp:kubestock-*",
                "arn:aws:rds:*:*:pg:kubestock-*",
                "arn:aws:rds:*:*:snapshot:kubestock-*"
            ]
        },
        {
            "Sid": "RDSDescribe",
            "Effect": "Allow",
            "Action": [
                "rds:Describe*",
                "rds:List*"
            ],
            "Resource": "*"
        },
        {
            "Sid": "IAMRoleManagement",
            "Effect": "Allow",
            "Action": [
                "iam:CreateRole",
                "iam:DeleteRole",
                "iam:GetRole",
                "iam:UpdateRole",
                "iam:UpdateAssumeRolePolicy",
                "iam:PutRolePolicy",
                "iam:DeleteRolePolicy",
                "iam:AttachRolePolicy",
                "iam:DetachRolePolicy",
                "iam:ListAttachedRolePolicies",
                "iam:ListRolePolicies",
                "iam:GetRolePolicy",
                "iam:TagRole",
                "iam:UntagRole",
                "iam:ListRoleTags"
            ],
            "Resource": [
                "arn:aws:iam::*:role/kubestock-*",
                "arn:aws:iam::*:role/KubeStock-*"
            ]
        },
        {
            "Sid": "IAMPolicyManagement",
            "Effect": "Allow",
            "Action": [
                "iam:CreatePolicy",
                "iam:DeletePolicy",
                "iam:GetPolicy",
                "iam:GetPolicyVersion",
                "iam:CreatePolicyVersion",
                "iam:DeletePolicyVersion",
                "iam:ListPolicyVersions",
                "iam:SetDefaultPolicyVersion",
                "iam:TagPolicy",
                "iam:UntagPolicy"
            ],
            "Resource": [
                "arn:aws:iam::*:policy/kubestock-*",
                "arn:aws:iam::*:policy/KubeStock-*"
            ]
        },
        {
            "Sid": "IAMInstanceProfileManagement",
            "Effect": "Allow",
            "Action": [
                "iam:CreateInstanceProfile",
                "iam:DeleteInstanceProfile",
                "iam:GetInstanceProfile",
                "iam:AddRoleToInstanceProfile",
                "iam:RemoveRoleFromInstanceProfile",
                "iam:ListInstanceProfiles",
                "iam:ListInstanceProfilesForRole",
                "iam:TagInstanceProfile",
                "iam:UntagInstanceProfile"
            ],
            "Resource": "arn:aws:iam::*:instance-profile/kubestock-*"
        },
        {
            "Sid": "IAMServiceLinkedRole",
            "Effect": "Allow",
            "Action": "iam:CreateServiceLinkedRole",
            "Resource": "arn:aws:iam::*:role/aws-service-role/*",
            "Condition": {
                "StringEquals": {
                    "iam:AWSServiceName": [
                        "elasticloadbalancing.amazonaws.com",
                        "autoscaling.amazonaws.com"
                    ]
                }
            }
        },
        {
            "Sid": "IAMPassRole",
            "Effect": "Allow",
            "Action": "iam:PassRole",
            "Resource": "arn:aws:iam::*:role/kubestock-*",
            "Condition": {
                "StringEquals": {
                    "iam:PassedToService": [
                        "ec2.amazonaws.com",
                        "lambda.amazonaws.com"
                    ]
                }
            }
        },
        {
            "Sid": "IAMReadOnly",
            "Effect": "Allow",
            "Action": [
                "iam:Get*",
                "iam:List*"
            ],
            "Resource": "*"
        }
    ]
}